simple_service_compose/__init__.py
simple_service_compose/py.typed
simple_service_compose/service.py
simple_service_compose-0.1.0.dist-info/licenses/LICENSE
simple_service_compose-0.1.0.dist-info/WHEEL
simple_service_compose-0.1.0.dist-info/METADATA
simple_service_compose-0.1.0.dist-info/RECORD
