Metadata-Version: 2.4
Name: simple-service-compose
Version: 0.1.0
Summary: Lightweight implementation of Finagle's Service and composable Filter types.
Author: Kendall Aubertot
Author-email: Kendall Aubertot <kendall.aubertot@techtraverse.io>
License-Expression: MIT
License-File: LICENSE
Requires-Python: >=3.12
Project-URL: Homepage, https://github.com/TechTraverse/simple-service-compose
Project-URL: Issues, https://github.com/TechTraverse/simple-service-compose/issues
